{
  "version": "7",
  "dialect": "postgresql",
  "entries": [
    {
      "idx": 0,
      "version": "7",
      "when": 1774546082560,
      "tag": "0000_milky_rocket_raccoon",
      "breakpoints": true
    },
    {
      "idx": 1,
      "version": "7",
      "when": 1774549418003,
      "tag": "0001_superb_madelyne_pryor",
      "breakpoints": true
    },
    {
      "idx": 2,
      "version": "7",
      "when": 1774564302767,
      "tag": "0002_striped_scarlet_spider",
      "breakpoints": true
    },
    {
      "idx": 3,
      "version": "7",
      "when": 1774566050063,
      "tag": "0003_bitter_shadowcat",
      "breakpoints": true
    },
    {
      "idx": 4,
      "version": "7",
      "when": 1774601816961,
      "tag": "0004_military_selene",
      "breakpoints": true
    },
    {
      "idx": 5,
      "version": "7",
      "when": 1774604474587,
      "tag": "0005_dapper_sersi",
      "breakpoints": true
    },
    {
      "idx": 6,
      "version": "7",
      "when": 1774633301700,
      "tag": "0006_mushy_network",
      "breakpoints": true
    },
    {
      "idx": 7,
      "version": "7",
      "when": 1774635076459,
      "tag": "0007_simple_moondragon",
      "breakpoints": true
    },
    {
      "idx": 8,
      "version": "7",
      "when": 1774651586611,
      "tag": "0008_wakeful_changeling",
      "breakpoints": true
    },
    {
      "idx": 9,
      "version": "7",
      "when": 1774655742181,
      "tag": "0009_fresh_diamondback",
      "breakpoints": true
    },
    {
      "idx": 10,
      "version": "7",
      "when": 1774726981182,
      "tag": "0010_shallow_lionheart",
      "breakpoints": true
    },
    {
      "idx": 11,
      "version": "7",
      "when": 1774728973138,
      "tag": "0011_brief_demogoblin",
      "breakpoints": true
    },
    {
      "idx": 12,
      "version": "7",
      "when": 1774745117763,
      "tag": "0012_tense_romulus",
      "breakpoints": true
    }
  ]
}